{
  "className": "bodytrackCHOP",
  "displayName": "bodytrackCHOP Class",
  "description": "This class inherits from the  CHOP class.\nIt references a specific Body Track CHOP.",
  "category": "General",
  "fileName": "BodytrackCHOP_Class.htm",
  "members": [
    {
      "name": "numChans",
      "id": "content",
      "returnType": "int",
      "readOnly": true,
      "description": "numChans member"
    },
    {
      "name": "numChans",
      "id": "bodyContent",
      "returnType": "int",
      "readOnly": true,
      "description": "numChans member"
    }
  ],
  "methods": []
}