{
  "className": "InputPoint",
  "displayName": "InputPoint Class",
  "description": "A Input Point is a special case of a Point object, only available in the Point SOP's parameters.",
  "category": "General",
  "fileName": "InputPoint_Class.htm",
  "members": [
    {
      "name": "color",
      "id": "content",
      "returnType": "TDU.Color",
      "readOnly": true,
      "description": "color member"
    },
    {
      "name": "color",
      "id": "bodyContent",
      "returnType": "TDU.Color",
      "readOnly": true,
      "description": "color member"
    }
  ],
  "methods": []
}