{
  "className": "moviefileoutTOP",
  "displayName": "moviefileoutTOP Class",
  "description": "This class inherits from the  TOP class.\nIt references a specific Movie File Out TOP.",
  "category": "General",
  "fileName": "MoviefileoutTOP_Class.htm",
  "members": [
    {
      "name": "writeCount",
      "id": "content",
      "returnType": "str",
      "readOnly": true,
      "description": "writeCount member"
    },
    {
      "name": "writeCount",
      "id": "bodyContent",
      "returnType": "str",
      "readOnly": true,
      "description": "writeCount member"
    }
  ],
  "methods": []
}